{
    "uuid": 329,
    "text": "scientists have based new research on previously developed methods in study of cancer cells",
    "graph": {
        "version": 1,
        "guid": "c9c4cc91-4990-41ed-ab0c-5d8447b405c3",
        "creator": "null",
        "relations": [
            {
                "label": "have",
                "id": "9d4a2021-1ee0-401e-a633-2782a97a189d",
                "index": 1,
                "postag": "NA"
            },
            {
                "label": "based",
                "id": "a2660717-8072-40a1-9393-0c00a6457b46",
                "index": 2,
                "postag": "NA"
            },
            {
                "label": "on",
                "id": "5191523c-c8aa-4eeb-b6e3-b265a20469e4",
                "index": 5,
                "postag": "NA"
            },
            {
                "label": "in",
                "id": "c41aa0d4-4d5c-4b0b-9411-a8c3b2762632",
                "index": 9,
                "postag": "NA"
            },
            {
                "label": "of",
                "id": "ecbbcd5b-cdc3-4251-a61d-5bd01cdd505e",
                "index": 11,
                "postag": "NA"
            }
        ],
        "concepts": [
            {
                "label": "scientists",
                "id": "79776953-a0b3-4119-ab7e-1040aac6b411",
                "index": 0,
                "postag": "NA"
            },
            {
                "label": "new",
                "id": "078b7dcc-01de-4464-a28a-dd45e514e193",
                "index": 3,
                "postag": "NA"
            },
            {
                "label": "research",
                "id": "c62ec6d3-e06c-4524-85dc-1786ecd979ee",
                "index": 4,
                "postag": "NA"
            },
            {
                "label": "previously",
                "id": "bc7839ad-29a1-4259-9110-88a429ba0704",
                "index": 6,
                "postag": "NA"
            },
            {
                "label": "developed",
                "id": "3bcb117b-e4e3-45cb-9193-32a7235bd7ed",
                "index": 7,
                "postag": "NA"
            },
            {
                "label": "methods",
                "id": "23a631be-de31-43ce-abb7-b130de174cec",
                "index": 8,
                "postag": "NA"
            },
            {
                "label": "study",
                "id": "c8a8e596-46e8-4d31-82ae-a6d73a69d5e9",
                "index": 10,
                "postag": "NA"
            },
            {
                "label": "cancer",
                "id": "ec2b7008-4cd9-46c3-9c8d-89ab0ce6d143",
                "index": 12,
                "postag": "NA"
            },
            {
                "label": "cells",
                "id": "9d4b34a1-840a-4b10-a938-868aa2deaaee",
                "index": 13,
                "postag": "NA"
            }
        ],
        "adjacencies": [
            {
                "nodeFrom": "79776953-a0b3-4119-ab7e-1040aac6b411",
                "nodeTo": "9d4a2021-1ee0-401e-a633-2782a97a189d",
                "index": 1,
                "order": "cr"
            },
            {
                "nodeFrom": "79776953-a0b3-4119-ab7e-1040aac6b411",
                "nodeTo": "a2660717-8072-40a1-9393-0c00a6457b46",
                "index": 2,
                "order": "cr"
            },
            {
                "nodeFrom": "9d4a2021-1ee0-401e-a633-2782a97a189d",
                "nodeTo": "078b7dcc-01de-4464-a28a-dd45e514e193",
                "index": 1,
                "order": "rc"
            },
            {
                "nodeFrom": "9d4a2021-1ee0-401e-a633-2782a97a189d",
                "nodeTo": "c62ec6d3-e06c-4524-85dc-1786ecd979ee",
                "index": 2,
                "order": "rc"
            },
            {
                "nodeFrom": "a2660717-8072-40a1-9393-0c00a6457b46",
                "nodeTo": "078b7dcc-01de-4464-a28a-dd45e514e193",
                "index": 1,
                "order": "rc"
            },
            {
                "nodeFrom": "a2660717-8072-40a1-9393-0c00a6457b46",
                "nodeTo": "c62ec6d3-e06c-4524-85dc-1786ecd979ee",
                "index": 2,
                "order": "rc"
            },
            {
                "nodeFrom": "078b7dcc-01de-4464-a28a-dd45e514e193",
                "nodeTo": "5191523c-c8aa-4eeb-b6e3-b265a20469e4",
                "index": 1,
                "order": "cr"
            },
            {
                "nodeFrom": "c62ec6d3-e06c-4524-85dc-1786ecd979ee",
                "nodeTo": "5191523c-c8aa-4eeb-b6e3-b265a20469e4",
                "index": 1,
                "order": "cr"
            },
            {
                "nodeFrom": "5191523c-c8aa-4eeb-b6e3-b265a20469e4",
                "nodeTo": "bc7839ad-29a1-4259-9110-88a429ba0704",
                "index": 1,
                "order": "rc"
            },
            {
                "nodeFrom": "5191523c-c8aa-4eeb-b6e3-b265a20469e4",
                "nodeTo": "3bcb117b-e4e3-45cb-9193-32a7235bd7ed",
                "index": 2,
                "order": "rc"
            },
            {
                "nodeFrom": "5191523c-c8aa-4eeb-b6e3-b265a20469e4",
                "nodeTo": "23a631be-de31-43ce-abb7-b130de174cec",
                "index": 3,
                "order": "rc"
            },
            {
                "nodeFrom": "bc7839ad-29a1-4259-9110-88a429ba0704",
                "nodeTo": "c41aa0d4-4d5c-4b0b-9411-a8c3b2762632",
                "index": 1,
                "order": "cr"
            },
            {
                "nodeFrom": "3bcb117b-e4e3-45cb-9193-32a7235bd7ed",
                "nodeTo": "c41aa0d4-4d5c-4b0b-9411-a8c3b2762632",
                "index": 1,
                "order": "cr"
            },
            {
                "nodeFrom": "23a631be-de31-43ce-abb7-b130de174cec",
                "nodeTo": "c41aa0d4-4d5c-4b0b-9411-a8c3b2762632",
                "index": 1,
                "order": "cr"
            },
            {
                "nodeFrom": "c41aa0d4-4d5c-4b0b-9411-a8c3b2762632",
                "nodeTo": "c8a8e596-46e8-4d31-82ae-a6d73a69d5e9",
                "index": 1,
                "order": "rc"
            },
            {
                "nodeFrom": "c8a8e596-46e8-4d31-82ae-a6d73a69d5e9",
                "nodeTo": "ecbbcd5b-cdc3-4251-a61d-5bd01cdd505e",
                "index": 1,
                "order": "cr"
            },
            {
                "nodeFrom": "ecbbcd5b-cdc3-4251-a61d-5bd01cdd505e",
                "nodeTo": "ec2b7008-4cd9-46c3-9c8d-89ab0ce6d143",
                "index": 1,
                "order": "rc"
            },
            {
                "nodeFrom": "ecbbcd5b-cdc3-4251-a61d-5bd01cdd505e",
                "nodeTo": "9d4b34a1-840a-4b10-a938-868aa2deaaee",
                "index": 2,
                "order": "rc"
            }
        ]
    },
    "created": "2014-12-15 14:38:21"
}