{
    "uuid": 796,
    "text": "New technology such as smartphones and tablets could be affecting how much sleep people get",
    "graph": {
        "version": 1,
        "guid": "500de319-79a8-4013-b869-b568cd9d3129",
        "creator": "null",
        "relations": [
            {
                "label": "such",
                "id": "061a880a-75ee-4782-b82e-92b5b792b980",
                "index": 2,
                "postag": "NA"
            },
            {
                "label": "as",
                "id": "859d2051-5975-4258-ab3d-765242dc5078",
                "index": 3,
                "postag": "NA"
            },
            {
                "label": "and",
                "id": "ad120661-4800-4cc5-94e4-a066504727cb",
                "index": 5,
                "postag": "NA"
            },
            {
                "label": "could",
                "id": "8bd1244c-c261-4e2a-9793-ba9925279b98",
                "index": 7,
                "postag": "NA"
            },
            {
                "label": "be",
                "id": "7ad4b298-b10d-4a9b-95cc-806d355e2e89",
                "index": 8,
                "postag": "NA"
            },
            {
                "label": "affecting",
                "id": "d40541e1-1995-422c-bc49-2ddc06963295",
                "index": 9,
                "postag": "NA"
            },
            {
                "label": "how",
                "id": "ed27311a-44d6-4a9a-915e-09d2d5e3eca6",
                "index": 10,
                "postag": "NA"
            },
            {
                "label": "get",
                "id": "9667935a-b421-4573-8bca-a3198ded21d7",
                "index": 14,
                "postag": "NA"
            }
        ],
        "concepts": [
            {
                "label": "New",
                "id": "b7165388-b3a7-4d74-b214-ec47b06e736d",
                "index": 0,
                "postag": "NA"
            },
            {
                "label": "technology",
                "id": "89290ddc-ca50-462a-b084-415d5a2161ec",
                "index": 1,
                "postag": "NA"
            },
            {
                "label": "smartphones",
                "id": "7e0cb35b-be39-4c04-a3a1-71e2e02c4530",
                "index": 4,
                "postag": "NA"
            },
            {
                "label": "tablets",
                "id": "37dcc191-be23-457b-8ca1-e95265340557",
                "index": 6,
                "postag": "NA"
            },
            {
                "label": "much",
                "id": "ac912361-3210-45d8-9d55-3a477676a331",
                "index": 11,
                "postag": "NA"
            },
            {
                "label": "sleep",
                "id": "b951c966-9dd9-4ecd-93d8-912b600e9d2e",
                "index": 12,
                "postag": "NA"
            },
            {
                "label": "people",
                "id": "130eb49a-9ac6-4447-b952-a7dec348815d",
                "index": 13,
                "postag": "NA"
            }
        ],
        "adjacencies": [
            {
                "nodeFrom": "b7165388-b3a7-4d74-b214-ec47b06e736d",
                "nodeTo": "061a880a-75ee-4782-b82e-92b5b792b980",
                "index": 1,
                "order": "cr"
            },
            {
                "nodeFrom": "89290ddc-ca50-462a-b084-415d5a2161ec",
                "nodeTo": "061a880a-75ee-4782-b82e-92b5b792b980",
                "index": 1,
                "order": "cr"
            },
            {
                "nodeFrom": "b7165388-b3a7-4d74-b214-ec47b06e736d",
                "nodeTo": "859d2051-5975-4258-ab3d-765242dc5078",
                "index": 2,
                "order": "cr"
            },
            {
                "nodeFrom": "89290ddc-ca50-462a-b084-415d5a2161ec",
                "nodeTo": "859d2051-5975-4258-ab3d-765242dc5078",
                "index": 2,
                "order": "cr"
            },
            {
                "nodeFrom": "859d2051-5975-4258-ab3d-765242dc5078",
                "nodeTo": "7e0cb35b-be39-4c04-a3a1-71e2e02c4530",
                "index": 1,
                "order": "rc"
            },
            {
                "nodeFrom": "061a880a-75ee-4782-b82e-92b5b792b980",
                "nodeTo": "7e0cb35b-be39-4c04-a3a1-71e2e02c4530",
                "index": 1,
                "order": "rc"
            },
            {
                "nodeFrom": "7e0cb35b-be39-4c04-a3a1-71e2e02c4530",
                "nodeTo": "ad120661-4800-4cc5-94e4-a066504727cb",
                "index": 1,
                "order": "cr"
            },
            {
                "nodeFrom": "ad120661-4800-4cc5-94e4-a066504727cb",
                "nodeTo": "37dcc191-be23-457b-8ca1-e95265340557",
                "index": 1,
                "order": "rc"
            },
            {
                "nodeFrom": "859d2051-5975-4258-ab3d-765242dc5078",
                "nodeTo": "37dcc191-be23-457b-8ca1-e95265340557",
                "index": 2,
                "order": "rc"
            },
            {
                "nodeFrom": "061a880a-75ee-4782-b82e-92b5b792b980",
                "nodeTo": "37dcc191-be23-457b-8ca1-e95265340557",
                "index": 2,
                "order": "rc"
            },
            {
                "nodeFrom": "b7165388-b3a7-4d74-b214-ec47b06e736d",
                "nodeTo": "8bd1244c-c261-4e2a-9793-ba9925279b98",
                "index": 3,
                "order": "cr"
            },
            {
                "nodeFrom": "b7165388-b3a7-4d74-b214-ec47b06e736d",
                "nodeTo": "7ad4b298-b10d-4a9b-95cc-806d355e2e89",
                "index": 4,
                "order": "cr"
            },
            {
                "nodeFrom": "b7165388-b3a7-4d74-b214-ec47b06e736d",
                "nodeTo": "d40541e1-1995-422c-bc49-2ddc06963295",
                "index": 5,
                "order": "cr"
            },
            {
                "nodeFrom": "89290ddc-ca50-462a-b084-415d5a2161ec",
                "nodeTo": "8bd1244c-c261-4e2a-9793-ba9925279b98",
                "index": 3,
                "order": "cr"
            },
            {
                "nodeFrom": "89290ddc-ca50-462a-b084-415d5a2161ec",
                "nodeTo": "7ad4b298-b10d-4a9b-95cc-806d355e2e89",
                "index": 4,
                "order": "cr"
            },
            {
                "nodeFrom": "89290ddc-ca50-462a-b084-415d5a2161ec",
                "nodeTo": "d40541e1-1995-422c-bc49-2ddc06963295",
                "index": 5,
                "order": "cr"
            },
            {
                "nodeFrom": "d40541e1-1995-422c-bc49-2ddc06963295",
                "nodeTo": "ac912361-3210-45d8-9d55-3a477676a331",
                "index": 1,
                "order": "rc"
            },
            {
                "nodeFrom": "d40541e1-1995-422c-bc49-2ddc06963295",
                "nodeTo": "b951c966-9dd9-4ecd-93d8-912b600e9d2e",
                "index": 2,
                "order": "rc"
            },
            {
                "nodeFrom": "d40541e1-1995-422c-bc49-2ddc06963295",
                "nodeTo": "130eb49a-9ac6-4447-b952-a7dec348815d",
                "index": 3,
                "order": "rc"
            },
            {
                "nodeFrom": "7ad4b298-b10d-4a9b-95cc-806d355e2e89",
                "nodeTo": "ac912361-3210-45d8-9d55-3a477676a331",
                "index": 1,
                "order": "rc"
            },
            {
                "nodeFrom": "7ad4b298-b10d-4a9b-95cc-806d355e2e89",
                "nodeTo": "b951c966-9dd9-4ecd-93d8-912b600e9d2e",
                "index": 2,
                "order": "rc"
            },
            {
                "nodeFrom": "7ad4b298-b10d-4a9b-95cc-806d355e2e89",
                "nodeTo": "130eb49a-9ac6-4447-b952-a7dec348815d",
                "index": 3,
                "order": "rc"
            },
            {
                "nodeFrom": "8bd1244c-c261-4e2a-9793-ba9925279b98",
                "nodeTo": "ac912361-3210-45d8-9d55-3a477676a331",
                "index": 1,
                "order": "rc"
            },
            {
                "nodeFrom": "8bd1244c-c261-4e2a-9793-ba9925279b98",
                "nodeTo": "b951c966-9dd9-4ecd-93d8-912b600e9d2e",
                "index": 2,
                "order": "rc"
            },
            {
                "nodeFrom": "8bd1244c-c261-4e2a-9793-ba9925279b98",
                "nodeTo": "130eb49a-9ac6-4447-b952-a7dec348815d",
                "index": 3,
                "order": "rc"
            },
            {
                "nodeFrom": "ed27311a-44d6-4a9a-915e-09d2d5e3eca6",
                "nodeTo": "ac912361-3210-45d8-9d55-3a477676a331",
                "index": 1,
                "order": "rc"
            },
            {
                "nodeFrom": "ed27311a-44d6-4a9a-915e-09d2d5e3eca6",
                "nodeTo": "b951c966-9dd9-4ecd-93d8-912b600e9d2e",
                "index": 2,
                "order": "rc"
            },
            {
                "nodeFrom": "ac912361-3210-45d8-9d55-3a477676a331",
                "nodeTo": "9667935a-b421-4573-8bca-a3198ded21d7",
                "index": 1,
                "order": "cr"
            },
            {
                "nodeFrom": "b951c966-9dd9-4ecd-93d8-912b600e9d2e",
                "nodeTo": "9667935a-b421-4573-8bca-a3198ded21d7",
                "index": 1,
                "order": "cr"
            },
            {
                "nodeFrom": "130eb49a-9ac6-4447-b952-a7dec348815d",
                "nodeTo": "9667935a-b421-4573-8bca-a3198ded21d7",
                "index": 1,
                "order": "cr"
            }
        ]
    },
    "created": "2015-01-15 22:05:32"
}